py_rally/ABI/IERC20.json
py_rally/ABI/IForwarder.json
py_rally/ABI/IRelayHub.json
py_rally/ABI/tokenFaucetData.json
py_rally/__init__.py
py_rally/abis.py
py_rally/builder.py
py_rally/config.py
py_rally/constants.py
py_rally/custom_types.py
py_rally/exceptions.py
py_rally/gsn.py
py_rally/helpers.py
py_rally/network.py
py_rally_sdk-1.1.1.dist-info/LICENSE.txt
py_rally_sdk-1.1.1.dist-info/METADATA
py_rally_sdk-1.1.1.dist-info/WHEEL
py_rally_sdk-1.1.1.dist-info/RECORD
