Metadata-Version: 2.1
Name: py-rally-sdk
Version: 1.1.1
Summary: Python client for RallyProtocol
Home-page: https://github.com/Tee-py/py-rally
License: MIT
Author: Tobiloba Emmanuel
Requires-Python: >=3.9,<4
Classifier: License :: OSI Approved :: MIT License
Classifier: Programming Language :: Python :: 3
Classifier: Programming Language :: Python :: 3.9
Classifier: Programming Language :: Python :: 3.10
Classifier: Programming Language :: Python :: 3.11
Requires-Dist: requests (==2.31.0)
Requires-Dist: web3 (==6.9.0)
